LICENSE
MANIFEST.in
README.md
setup.py
cmsplugin_container/__init__.py
cmsplugin_container/admin.py
cmsplugin_container/cms_plugins.py
cmsplugin_container/models.py
cmsplugin_container/tests.py
cmsplugin_container/views.py
cmsplugin_container.egg-info/PKG-INFO
cmsplugin_container.egg-info/SOURCES.txt
cmsplugin_container.egg-info/dependency_links.txt
cmsplugin_container.egg-info/top_level.txt
cmsplugin_container/migrations/0001_initial.py
cmsplugin_container/migrations/__init__.py
cmsplugin_container/templates/container/carousel.html
cmsplugin_container/templates/container/container.html