Metadata-Version: 1.1
Name: cmsplugin-container
Version: 1.1.2
Summary: Simple django CMS plugin to render sub-plugins in different templates
Home-page: https://github.com/misli/cmsplugin-container
Author: Jakub Dorňák
Author-email: jakub.dornak@misli.cz
License: BSD
Platform: UNKNOWN
Classifier: Development Status :: 4 - Beta
Classifier: Environment :: Web Environment
Classifier: Framework :: Django
Classifier: Intended Audience :: Developers
Classifier: License :: OSI Approved :: BSD License
Classifier: Operating System :: OS Independent
Classifier: Programming Language :: Python
Classifier: Programming Language :: Python :: 2.7
Classifier: Programming Language :: Python :: 3.4
